dockering/__init__.py
dockering/config_building.py
dockering/core.py
dockering/exceptions.py
dockering/utils.py
onap_dcae_dockering-1.4.1.dist-info/LICENSE.txt
onap_dcae_dockering-1.4.1.dist-info/METADATA
onap_dcae_dockering-1.4.1.dist-info/WHEEL
onap_dcae_dockering-1.4.1.dist-info/top_level.txt
onap_dcae_dockering-1.4.1.dist-info/RECORD
